semser/__init__.py
semser/semantic_search.py
semser-0.2.1.dist-info/METADATA
semser-0.2.1.dist-info/WHEEL
semser-0.2.1.dist-info/entry_points.txt
semser-0.2.1.dist-info/RECORD
