Metadata-Version: 2.1
Name: semser
Version: 0.2.1
Summary: A simple Semantic Scholar search CLI.
Home-page: https://github.com/fergusfettes/semser
Author: fergus
Author-email: fergusfettes@gmail.com
Requires-Python: >=3.8,<4.0
Classifier: Programming Language :: Python :: 3
Classifier: Programming Language :: Python :: 3.8
Classifier: Programming Language :: Python :: 3.9
Classifier: Programming Language :: Python :: 3.10
Classifier: Programming Language :: Python :: 3.11
Requires-Dist: pyzotero (>=1.5.18,<2.0.0)
Requires-Dist: requests (>=2.31.0)
Requires-Dist: rich (>=13.7.0)
Requires-Dist: semanticscholar (>=0.7.0)
Requires-Dist: typer (>=0.9.0)
